pyFileArchiver/__init__.py
pyFileArchiver/archiver.py
tests/__init__.py
tests/test_archiver.py
pyFileArchiverGrigoriew-1.0.0.dist-info/METADATA
pyFileArchiverGrigoriew-1.0.0.dist-info/WHEEL
pyFileArchiverGrigoriew-1.0.0.dist-info/top_level.txt
pyFileArchiverGrigoriew-1.0.0.dist-info/RECORD
