Metadata-Version: 2.1
Name: pyFileArchiverGrigoriew
Version: 1.0.0
Summary: Python archiver
Home-page: UNKNOWN
Author: Grigoriew N.A.
Author-email: nickita.grigoriew2012@yandex.ru
License: UNKNOWN
Platform: any
Requires-Python: >=3.7
